{"start":"2022-10-05","end":"2023-10-04","package":"ngx-file-drop","downloads":[{"downloads":29274,"day":"2022-10-05"},{"downloads":30569,"day":"2022-10-06"},{"downloads":30109,"day":"2022-10-07"},{"downloads":23408,"day":"2022-10-08"},{"downloads":22935,"day":"2022-10-09"},{"downloads":29669,"day":"2022-10-10"},{"downloads":19949,"day":"2022-10-11"},{"downloads":18723,"day":"2022-10-12"},{"downloads":19383,"day":"2022-10-13"},{"downloads":17448,"day":"2022-10-14"},{"downloads":14763,"day":"2022-10-15"},{"downloads":19515,"day":"2022-10-16"},{"downloads":25250,"day":"2022-10-17"},{"downloads":20576,"day":"2022-10-18"},{"downloads":22816,"day":"2022-10-19"},{"downloads":30289,"day":"2022-10-20"},{"downloads":30728,"day":"2022-10-21"},{"downloads":23141,"day":"2022-10-22"},{"downloads":23781,"day":"2022-10-23"},{"downloads":31023,"day":"2022-10-24"},{"downloads":31741,"day":"2022-10-25"},{"downloads":31959,"day":"2022-10-26"},{"downloads":23796,"day":"2022-10-27"},{"downloads":7792,"day":"2022-10-28"},{"downloads":949,"day":"2022-10-29"},{"downloads":1253,"day":"2022-10-30"},{"downloads":8471,"day":"2022-10-31"},{"downloads":8186,"day":"2022-11-01"},{"downloads":9380,"day":"2022-11-02"},{"downloads":9664,"day":"2022-11-03"},{"downloads":7854,"day":"2022-11-04"},{"downloads":913,"day":"2022-11-05"},{"downloads":1337,"day":"2022-11-06"},{"downloads":8942,"day":"2022-11-07"},{"downloads":9398,"day":"2022-11-08"},{"downloads":9260,"day":"2022-11-09"},{"downloads":9110,"day":"2022-11-10"},{"downloads":6592,"day":"2022-11-11"},{"downloads":1012,"day":"2022-11-12"},{"downloads":1255,"day":"2022-11-13"},{"downloads":8960,"day":"2022-11-14"},{"downloads":9783,"day":"2022-11-15"},{"downloads":9669,"day":"2022-11-16"},{"downloads":9170,"day":"2022-11-17"},{"downloads":7847,"day":"2022-11-18"},{"downloads":993,"day":"2022-11-19"},{"downloads":1373,"day":"2022-11-20"},{"downloads":9131,"day":"2022-11-21"},{"downloads":9592,"day":"2022-11-22"},{"downloads":9226,"day":"2022-11-23"},{"downloads":8091,"day":"2022-11-24"},{"downloads":7111,"day":"2022-11-25"},{"downloads":897,"day":"2022-11-26"},{"downloads":1259,"day":"2022-11-27"},{"downloads":9868,"day":"2022-11-28"},{"downloads":10014,"day":"2022-11-29"},{"downloads":9528,"day":"2022-11-30"},{"downloads":9601,"day":"2022-12-01"},{"downloads":8349,"day":"2022-12-02"},{"downloads":1213,"day":"2022-12-03"},{"downloads":1414,"day":"2022-12-04"},{"downloads":9641,"day":"2022-12-05"},{"downloads":9802,"day":"2022-12-06"},{"downloads":9679,"day":"2022-12-07"},{"downloads":8985,"day":"2022-12-08"},{"downloads":7640,"day":"2022-12-09"},{"downloads":898,"day":"2022-12-10"},{"downloads":1372,"day":"2022-12-11"},{"downloads":9152,"day":"2022-12-12"},{"downloads":10037,"day":"2022-12-13"},{"downloads":8996,"day":"2022-12-14"},{"downloads":9283,"day":"2022-12-15"},{"downloads":7308,"day":"2022-12-16"},{"downloads":965,"day":"2022-12-17"},{"downloads":1192,"day":"2022-12-18"},{"downloads":8358,"day":"2022-12-19"},{"downloads":9117,"day":"2022-12-20"},{"downloads":8262,"day":"2022-12-21"},{"downloads":7669,"day":"2022-12-22"},{"downloads":5648,"day":"2022-12-23"},{"downloads":821,"day":"2022-12-24"},{"downloads":781,"day":"2022-12-25"},{"downloads":3207,"day":"2022-12-26"},{"downloads":4781,"day":"2022-12-27"},{"downloads":4968,"day":"2022-12-28"},{"downloads":4945,"day":"2022-12-29"},{"downloads":3514,"day":"2022-12-30"},{"downloads":624,"day":"2022-12-31"},{"downloads":926,"day":"2023-01-01"},{"downloads":4702,"day":"2023-01-02"},{"downloads":8146,"day":"2023-01-03"},{"downloads":7744,"day":"2023-01-04"},{"downloads":8574,"day":"2023-01-05"},{"downloads":5949,"day":"2023-01-06"},{"downloads":955,"day":"2023-01-07"},{"downloads":1378,"day":"2023-01-08"},{"downloads":9018,"day":"2023-01-09"},{"downloads":9835,"day":"2023-01-10"},{"downloads":9606,"day":"2023-01-11"},{"downloads":9635,"day":"2023-01-12"},{"downloads":8112,"day":"2023-01-13"},{"downloads":1089,"day":"2023-01-14"},{"downloads":1785,"day":"2023-01-15"},{"downloads":9030,"day":"2023-01-16"},{"downloads":10406,"day":"2023-01-17"},{"downloads":9451,"day":"2023-01-18"},{"downloads":9752,"day":"2023-01-19"},{"downloads":8446,"day":"2023-01-20"},{"downloads":1028,"day":"2023-01-21"},{"downloads":1310,"day":"2023-01-22"},{"downloads":9357,"day":"2023-01-23"},{"downloads":10073,"day":"2023-01-24"},{"downloads":9512,"day":"2023-01-25"},{"downloads":8840,"day":"2023-01-26"},{"downloads":8612,"day":"2023-01-27"},{"downloads":1180,"day":"2023-01-28"},{"downloads":1651,"day":"2023-01-29"},{"downloads":10284,"day":"2023-01-30"},{"downloads":10549,"day":"2023-01-31"},{"downloads":9796,"day":"2023-02-01"},{"downloads":9574,"day":"2023-02-02"},{"downloads":8554,"day":"2023-02-03"},{"downloads":1139,"day":"2023-02-04"},{"downloads":1343,"day":"2023-02-05"},{"downloads":9400,"day":"2023-02-06"},{"downloads":10251,"day":"2023-02-07"},{"downloads":10044,"day":"2023-02-08"},{"downloads":10003,"day":"2023-02-09"},{"downloads":8857,"day":"2023-02-10"},{"downloads":933,"day":"2023-02-11"},{"downloads":1388,"day":"2023-02-12"},{"downloads":10051,"day":"2023-02-13"},{"downloads":10416,"day":"2023-02-14"},{"downloads":10148,"day":"2023-02-15"},{"downloads":10448,"day":"2023-02-16"},{"downloads":8891,"day":"2023-02-17"},{"downloads":961,"day":"2023-02-18"},{"downloads":8511,"day":"2023-02-19"},{"downloads":23666,"day":"2023-02-20"},{"downloads":28249,"day":"2023-02-21"},{"downloads":27739,"day":"2023-02-22"},{"downloads":28150,"day":"2023-02-23"},{"downloads":27367,"day":"2023-02-24"},{"downloads":20907,"day":"2023-02-25"},{"downloads":21658,"day":"2023-02-26"},{"downloads":27762,"day":"2023-02-27"},{"downloads":28878,"day":"2023-02-28"},{"downloads":28812,"day":"2023-03-01"},{"downloads":29614,"day":"2023-03-02"},{"downloads":28645,"day":"2023-03-03"},{"downloads":21604,"day":"2023-03-04"},{"downloads":20580,"day":"2023-03-05"},{"downloads":30562,"day":"2023-03-06"},{"downloads":26600,"day":"2023-03-07"},{"downloads":27491,"day":"2023-03-08"},{"downloads":31110,"day":"2023-03-09"},{"downloads":29775,"day":"2023-03-10"},{"downloads":21747,"day":"2023-03-11"},{"downloads":22629,"day":"2023-03-12"},{"downloads":30765,"day":"2023-03-13"},{"downloads":31223,"day":"2023-03-14"},{"downloads":30213,"day":"2023-03-15"},{"downloads":31659,"day":"2023-03-16"},{"downloads":30006,"day":"2023-03-17"},{"downloads":21780,"day":"2023-03-18"},{"downloads":22114,"day":"2023-03-19"},{"downloads":30583,"day":"2023-03-20"},{"downloads":31631,"day":"2023-03-21"},{"downloads":30794,"day":"2023-03-22"},{"downloads":32263,"day":"2023-03-23"},{"downloads":29866,"day":"2023-03-24"},{"downloads":21495,"day":"2023-03-25"},{"downloads":21559,"day":"2023-03-26"},{"downloads":30499,"day":"2023-03-27"},{"downloads":30556,"day":"2023-03-28"},{"downloads":30668,"day":"2023-03-29"},{"downloads":30614,"day":"2023-03-30"},{"downloads":27438,"day":"2023-03-31"},{"downloads":20307,"day":"2023-04-01"},{"downloads":20657,"day":"2023-04-02"},{"downloads":22246,"day":"2023-04-03"},{"downloads":25266,"day":"2023-04-04"},{"downloads":29773,"day":"2023-04-05"},{"downloads":28698,"day":"2023-04-06"},{"downloads":25853,"day":"2023-04-07"},{"downloads":21782,"day":"2023-04-08"},{"downloads":22040,"day":"2023-04-09"},{"downloads":27127,"day":"2023-04-10"},{"downloads":30900,"day":"2023-04-11"},{"downloads":31109,"day":"2023-04-12"},{"downloads":31052,"day":"2023-04-13"},{"downloads":20690,"day":"2023-04-14"},{"downloads":9714,"day":"2023-04-15"},{"downloads":10844,"day":"2023-04-16"},{"downloads":19557,"day":"2023-04-17"},{"downloads":20048,"day":"2023-04-18"},{"downloads":19226,"day":"2023-04-19"},{"downloads":19021,"day":"2023-04-20"},{"downloads":16703,"day":"2023-04-21"},{"downloads":9667,"day":"2023-04-22"},{"downloads":14868,"day":"2023-04-23"},{"downloads":24420,"day":"2023-04-24"},{"downloads":22538,"day":"2023-04-25"},{"downloads":18463,"day":"2023-04-26"},{"downloads":18878,"day":"2023-04-27"},{"downloads":17052,"day":"2023-04-28"},{"downloads":10040,"day":"2023-04-29"},{"downloads":11429,"day":"2023-04-30"},{"downloads":13092,"day":"2023-05-01"},{"downloads":18656,"day":"2023-05-02"},{"downloads":18301,"day":"2023-05-03"},{"downloads":25285,"day":"2023-05-04"},{"downloads":27967,"day":"2023-05-05"},{"downloads":20034,"day":"2023-05-06"},{"downloads":14528,"day":"2023-05-07"},{"downloads":17692,"day":"2023-05-08"},{"downloads":18711,"day":"2023-05-09"},{"downloads":18356,"day":"2023-05-10"},{"downloads":18115,"day":"2023-05-11"},{"downloads":16772,"day":"2023-05-12"},{"downloads":9683,"day":"2023-05-13"},{"downloads":10563,"day":"2023-05-14"},{"downloads":18603,"day":"2023-05-15"},{"downloads":18914,"day":"2023-05-16"},{"downloads":19020,"day":"2023-05-17"},{"downloads":17565,"day":"2023-05-18"},{"downloads":15995,"day":"2023-05-19"},{"downloads":9356,"day":"2023-05-20"},{"downloads":11213,"day":"2023-05-21"},{"downloads":18519,"day":"2023-05-22"},{"downloads":18778,"day":"2023-05-23"},{"downloads":18368,"day":"2023-05-24"},{"downloads":18155,"day":"2023-05-25"},{"downloads":16525,"day":"2023-05-26"},{"downloads":9581,"day":"2023-05-27"},{"downloads":10595,"day":"2023-05-28"},{"downloads":15813,"day":"2023-05-29"},{"downloads":18694,"day":"2023-05-30"},{"downloads":18887,"day":"2023-05-31"},{"downloads":19476,"day":"2023-06-01"},{"downloads":17509,"day":"2023-06-02"},{"downloads":16305,"day":"2023-06-03"},{"downloads":19037,"day":"2023-06-04"},{"downloads":23679,"day":"2023-06-05"},{"downloads":19470,"day":"2023-06-06"},{"downloads":19303,"day":"2023-06-07"},{"downloads":18283,"day":"2023-06-08"},{"downloads":17858,"day":"2023-06-09"},{"downloads":10412,"day":"2023-06-10"},{"downloads":12137,"day":"2023-06-11"},{"downloads":17725,"day":"2023-06-12"},{"downloads":18679,"day":"2023-06-13"},{"downloads":19303,"day":"2023-06-14"},{"downloads":18909,"day":"2023-06-15"},{"downloads":15964,"day":"2023-06-16"},{"downloads":9688,"day":"2023-06-17"},{"downloads":10153,"day":"2023-06-18"},{"downloads":17981,"day":"2023-06-19"},{"downloads":19511,"day":"2023-06-20"},{"downloads":19609,"day":"2023-06-21"},{"downloads":18930,"day":"2023-06-22"},{"downloads":17158,"day":"2023-06-23"},{"downloads":10346,"day":"2023-06-24"},{"downloads":11478,"day":"2023-06-25"},{"downloads":19029,"day":"2023-06-26"},{"downloads":18827,"day":"2023-06-27"},{"downloads":18697,"day":"2023-06-28"},{"downloads":19063,"day":"2023-06-29"},{"downloads":17270,"day":"2023-06-30"},{"downloads":0,"day":"2023-07-01"},{"downloads":8851,"day":"2023-07-02"},{"downloads":13535,"day":"2023-07-03"},{"downloads":13655,"day":"2023-07-04"},{"downloads":15076,"day":"2023-07-05"},{"downloads":17779,"day":"2023-07-06"},{"downloads":17236,"day":"2023-07-07"},{"downloads":9373,"day":"2023-07-08"},{"downloads":10655,"day":"2023-07-09"},{"downloads":18137,"day":"2023-07-10"},{"downloads":18710,"day":"2023-07-11"},{"downloads":18063,"day":"2023-07-12"},{"downloads":18269,"day":"2023-07-13"},{"downloads":16332,"day":"2023-07-14"},{"downloads":9516,"day":"2023-07-15"},{"downloads":10311,"day":"2023-07-16"},{"downloads":18035,"day":"2023-07-17"},{"downloads":19675,"day":"2023-07-18"},{"downloads":18268,"day":"2023-07-19"},{"downloads":17445,"day":"2023-07-20"},{"downloads":7943,"day":"2023-07-21"},{"downloads":1119,"day":"2023-07-22"},{"downloads":1515,"day":"2023-07-23"},{"downloads":9265,"day":"2023-07-24"},{"downloads":10541,"day":"2023-07-25"},{"downloads":10307,"day":"2023-07-26"},{"downloads":10174,"day":"2023-07-27"},{"downloads":7744,"day":"2023-07-28"},{"downloads":1079,"day":"2023-07-29"},{"downloads":9122,"day":"2023-07-30"},{"downloads":17674,"day":"2023-07-31"},{"downloads":17912,"day":"2023-08-01"},{"downloads":17552,"day":"2023-08-02"},{"downloads":17983,"day":"2023-08-03"},{"downloads":16871,"day":"2023-08-04"},{"downloads":9724,"day":"2023-08-05"},{"downloads":10058,"day":"2023-08-06"},{"downloads":15599,"day":"2023-08-07"},{"downloads":16776,"day":"2023-08-08"},{"downloads":16767,"day":"2023-08-09"},{"downloads":17464,"day":"2023-08-10"},{"downloads":15596,"day":"2023-08-11"},{"downloads":8427,"day":"2023-08-12"},{"downloads":9852,"day":"2023-08-13"},{"downloads":21552,"day":"2023-08-14"},{"downloads":21692,"day":"2023-08-15"},{"downloads":20607,"day":"2023-08-16"},{"downloads":31145,"day":"2023-08-17"},{"downloads":21563,"day":"2023-08-18"},{"downloads":9083,"day":"2023-08-19"},{"downloads":10657,"day":"2023-08-20"},{"downloads":17426,"day":"2023-08-21"},{"downloads":17673,"day":"2023-08-22"},{"downloads":16960,"day":"2023-08-23"},{"downloads":17573,"day":"2023-08-24"},{"downloads":15761,"day":"2023-08-25"},{"downloads":8919,"day":"2023-08-26"},{"downloads":11543,"day":"2023-08-27"},{"downloads":16666,"day":"2023-08-28"},{"downloads":18020,"day":"2023-08-29"},{"downloads":16687,"day":"2023-08-30"},{"downloads":17510,"day":"2023-08-31"},{"downloads":18453,"day":"2023-09-01"},{"downloads":13686,"day":"2023-09-02"},{"downloads":9545,"day":"2023-09-03"},{"downloads":12822,"day":"2023-09-04"},{"downloads":16032,"day":"2023-09-05"},{"downloads":16384,"day":"2023-09-06"},{"downloads":16363,"day":"2023-09-07"},{"downloads":22319,"day":"2023-09-08"},{"downloads":14677,"day":"2023-09-09"},{"downloads":11109,"day":"2023-09-10"},{"downloads":18508,"day":"2023-09-11"},{"downloads":18639,"day":"2023-09-12"},{"downloads":18352,"day":"2023-09-13"},{"downloads":17726,"day":"2023-09-14"},{"downloads":18813,"day":"2023-09-15"},{"downloads":23902,"day":"2023-09-16"},{"downloads":26501,"day":"2023-09-17"},{"downloads":26329,"day":"2023-09-18"},{"downloads":16566,"day":"2023-09-19"},{"downloads":9989,"day":"2023-09-20"},{"downloads":9968,"day":"2023-09-21"},{"downloads":8226,"day":"2023-09-22"},{"downloads":1009,"day":"2023-09-23"},{"downloads":1099,"day":"2023-09-24"},{"downloads":9446,"day":"2023-09-25"},{"downloads":10590,"day":"2023-09-26"},{"downloads":10473,"day":"2023-09-27"},{"downloads":9299,"day":"2023-09-28"},{"downloads":7746,"day":"2023-09-29"},{"downloads":810,"day":"2023-09-30"},{"downloads":1402,"day":"2023-10-01"},{"downloads":8320,"day":"2023-10-02"},{"downloads":9461,"day":"2023-10-03"},{"downloads":10417,"day":"2023-10-04"}]}